bepr/__init__.py
bepr/bepr.py
bepr-0.0.6.dist-info/LICENSE
bepr-0.0.6.dist-info/METADATA
bepr-0.0.6.dist-info/WHEEL
bepr-0.0.6.dist-info/dependency_links.txt
bepr-0.0.6.dist-info/top_level.txt
bepr-0.0.6.dist-info/RECORD
