Metadata-Version: 2.1
Name: bepr
Version: 0.0.6
Summary: A python package for modelling Bacteriophage effect on parasitism resistance.
Home-page: https://github.com/GabrielRPalma/bepr
Author: Gabriel Rodrigues Palma
Author-email: gabrielrpalma2@gmail.com
License: MIT license
Keywords: bepr
Classifier: Development Status :: 2 - Pre-Alpha
Classifier: Intended Audience :: Developers
Classifier: License :: OSI Approved :: MIT License
Classifier: Natural Language :: English
Classifier: Programming Language :: Python :: 3
Classifier: Programming Language :: Python :: 3.7
Classifier: Programming Language :: Python :: 3.8
Classifier: Programming Language :: Python :: 3.9
Requires-Python: >=3.7
License-File: LICENSE
Requires-Dist: numpy (==1.22.3)
Requires-Dist: pandas (==1.4.2)
Requires-Dist: matplotlib (==3.5.2)
Requires-Dist: scipy (==1.8.1)
